rabbitmq_request_response/__init__.py
rabbitmq_request_response/amqplib.py
rabbitmq_request_response/elasticsearchsaver.py
rabbitmq_request_response/exceptionreporter.py
rabbitmq_request_response/supports.py
rabbitmq_request_response-0.0.2.dist-info/METADATA
rabbitmq_request_response-0.0.2.dist-info/WHEEL
rabbitmq_request_response-0.0.2.dist-info/top_level.txt
rabbitmq_request_response-0.0.2.dist-info/RECORD
