Metadata-Version: 2.1
Name: rabbitmq-request-response
Version: 0.0.2
Summary: Common python package
Home-page: https://gitee.com/starview/pulsar-request-response
Author: mengzengshan
Author-email: 378077287@qq.com
License: UNKNOWN
Platform: UNKNOWN
Classifier: Programming Language :: Python :: 3
Classifier: License :: OSI Approved :: MIT License
Classifier: Operating System :: OS Independent
Requires-Python: >=3.6
Requires-Dist: elasticsearch ==7.12.0
Requires-Dist: pika
Requires-Dist: tornado
